sanic_routes/RouteParser.py
sanic_routes/__init__.py
sanic_routes/exceptions.py
sanic_routes/objectify.py
sanic_routes-1.0.14.dist-info/METADATA
sanic_routes-1.0.14.dist-info/WHEEL
sanic_routes-1.0.14.dist-info/top_level.txt
sanic_routes-1.0.14.dist-info/RECORD
